modelly_client/__init__.py
modelly_client/client.py
modelly_client/compatibility.py
modelly_client/data_classes.py
modelly_client/documentation.py
modelly_client/exceptions.py
modelly_client/media_data.py
modelly_client/package.json
modelly_client/serializing.py
modelly_client/types.json
modelly_client/utils.py
modelly_client/cli/__init__.py
modelly_client/cli/deploy_discord.py
modelly_client/templates/discord_chat.py
modelly_client-1.0.0.dist-info/METADATA
modelly_client-1.0.0.dist-info/WHEEL
modelly_client-1.0.0.dist-info/RECORD
