Metadata-Version: 2.4
Name: modelly_client
Version: 1.0.0
Summary: Python library for easily interacting with trained machine learning models
Project-URL: Homepage, https://github.com/khulnasoft/modelly
Author-email: Abubakar Abid <modelly-team@huggingface.co>, Ali Abid <modelly-team@huggingface.co>, Ali Abdalla <modelly-team@huggingface.co>, Dawood Khan <modelly-team@huggingface.co>, Ahsen Khaliq <modelly-team@huggingface.co>, Pete Allen <modelly-team@huggingface.co>, Freddy Boulton <modelly-team@huggingface.co>
License-Expression: Apache-2.0
Keywords: API,client,machine learning
Classifier: Development Status :: 4 - Beta
Classifier: License :: OSI Approved :: Apache Software License
Classifier: Operating System :: OS Independent
Classifier: Programming Language :: Python :: 3
Classifier: Programming Language :: Python :: 3 :: Only
Classifier: Programming Language :: Python :: 3.8
Classifier: Programming Language :: Python :: 3.9
Classifier: Programming Language :: Python :: 3.10
Classifier: Programming Language :: Python :: 3.11
Classifier: Topic :: Scientific/Engineering
Classifier: Topic :: Scientific/Engineering :: Artificial Intelligence
Classifier: Topic :: Software Development :: User Interfaces
Requires-Python: >=3.10
Requires-Dist: fsspec
Requires-Dist: httpx>=0.24.1
Requires-Dist: huggingface-hub>=0.19.3
Requires-Dist: packaging
Requires-Dist: typing-extensions~=4.0
Requires-Dist: websockets<15.0,>=10.0
